py591/__init__.py
py591/app.py
py591/parse.py
py591-0.0.3.dist-info/LICENSE
py591-0.0.3.dist-info/WHEEL
py591-0.0.3.dist-info/METADATA
py591-0.0.3.dist-info/RECORD
